badger_utils/__init__.py
badger_utils/coingecko_utils.py
badger_utils/constants.py
badger_utils/digg_utils.py
badger_utils/ethplorer_utils.py
badger_utils/network_manager.py
badger_utils/proxy_utils.py
badger_utils/time_utils.py
badger_utils/tx_timer.py
badger_utils/utils.py
badger_utils/gas_utils/__init__.py
badger_utils/gas_utils/analyze_gas.py
badger_utils/gas_utils/gas_now_compatible_strategy.py
badger_utils/gas_utils/gas_utils.py
badger_utils/registry/__init__.py
badger_utils/registry/artifacts.py
badger_utils/registry/base_registry.py
badger_utils/registry/bsc_registry.py
badger_utils/registry/chain_registry.py
badger_utils/registry/eth_registry.py
badger_utils/registry/on_chain_registries.py
badger_utils/registry/registries.py
badger_utils/registry/yearn_registry.py
badger_utils/registry/dependency-artifacts/__init__.py
badger_utils/registry/dependency-artifacts/aragon/Agent.json
badger_utils/registry/dependency-artifacts/aragon/CompanyTemplate.json
badger_utils/registry/dependency-artifacts/aragon/Finance.json
badger_utils/registry/dependency-artifacts/aragon/MiniMeToken.json
badger_utils/registry/dependency-artifacts/aragon/TokenManager.json
badger_utils/registry/dependency-artifacts/aragon/Vault.json
badger_utils/registry/dependency-artifacts/aragon/Voting.json
badger_utils/registry/dependency-artifacts/digg/Mock.json
badger_utils/registry/dependency-artifacts/gnosis-safe/Executor.json
badger_utils/registry/dependency-artifacts/gnosis-safe/GnosisSafe.json
badger_utils/registry/dependency-artifacts/gnosis-safe/GnosisSafeProxy.json
badger_utils/registry/dependency-artifacts/gnosis-safe/GnosisSafeProxyFactory.json
badger_utils/registry/dependency-artifacts/gnosis-safe/MasterCopy.json
badger_utils/registry/dependency-artifacts/gnosis-safe/MultiSend.json
badger_utils/registry/dependency-artifacts/gnosis-safe/ProxyFactory.json
badger_utils/registry/dependency-artifacts/multicall/Multicall.json
badger_utils-0.2.5.dist-info/LICENSE
badger_utils-0.2.5.dist-info/METADATA
badger_utils-0.2.5.dist-info/WHEEL
badger_utils-0.2.5.dist-info/top_level.txt
badger_utils-0.2.5.dist-info/RECORD
