Metadata-Version: 2.1
Name: badger-utils
Version: 0.2.5
Summary: Badger utils and shared code
Home-page: https://github.com/SHAKOTN/badger-utils
Author: Andrii Kulikov
Author-email: blaynemono@gmail.com
License: MIT
Keywords: badger-utils
Platform: UNKNOWN
Classifier: License :: OSI Approved :: MIT License
Classifier: Intended Audience :: Developers
Classifier: Programming Language :: Python :: 3
Requires-Python: >=3.7,<4
License-File: LICENSE
Requires-Dist: dotmap
Requires-Dist: eth-brownie (>=1.14.0)
Requires-Dist: numpy (==1.21.0)
Requires-Dist: elasticsearch (==7.10.1)
